<?xml version="1.0" encoding="UTF-8" standalone="yes"?>
<template encoding-version="1.3">
    <description></description>
    <groupId>f5bf31c6-bd66-4a08-9cb2-10cc4e41531e</groupId>
    <name>{{ nifi_template_name }}</name>
    <snippet>
        <connections>
            <id>5bc6cd36-af92-3ce9-0000-000000000000</id>
            <parentGroupId>318f3af6-162f-3813-0000-000000000000</parentGroupId>
            <backPressureDataSizeThreshold>1 GB</backPressureDataSizeThreshold>
            <backPressureObjectThreshold>10000</backPressureObjectThreshold>
            <destination>
                <groupId>318f3af6-162f-3813-0000-000000000000</groupId>
                <id>468434ca-b8a4-3056-0000-000000000000</id>
                <type>PROCESSOR</type>
            </destination>
            <flowFileExpiration>0 sec</flowFileExpiration>
            <labelIndex>1</labelIndex>
            <loadBalanceCompression>DO_NOT_COMPRESS</loadBalanceCompression>
            <loadBalancePartitionAttribute></loadBalancePartitionAttribute>
            <loadBalanceStatus>LOAD_BALANCE_NOT_CONFIGURED</loadBalanceStatus>
            <loadBalanceStrategy>DO_NOT_LOAD_BALANCE</loadBalanceStrategy>
            <name></name>
            <selectedRelationships>success</selectedRelationships>
            <source>
                <groupId>318f3af6-162f-3813-0000-000000000000</groupId>
                <id>028b1655-7bb8-32dc-0000-000000000000</id>
                <type>PROCESSOR</type>
            </source>
            <zIndex>0</zIndex>
        </connections>
        <connections>
            <id>7d5178c8-dd22-31ac-0000-000000000000</id>
            <parentGroupId>318f3af6-162f-3813-0000-000000000000</parentGroupId>
            <backPressureDataSizeThreshold>1 GB</backPressureDataSizeThreshold>
            <backPressureObjectThreshold>10000</backPressureObjectThreshold>
            <destination>
                <groupId>318f3af6-162f-3813-0000-000000000000</groupId>
                <id>3f1fc979-fb58-3119-0000-000000000000</id>
                <type>PROCESSOR</type>
            </destination>
            <flowFileExpiration>0 sec</flowFileExpiration>
            <labelIndex>1</labelIndex>
            <loadBalanceCompression>DO_NOT_COMPRESS</loadBalanceCompression>
            <loadBalancePartitionAttribute></loadBalancePartitionAttribute>
            <loadBalanceStatus>LOAD_BALANCE_NOT_CONFIGURED</loadBalanceStatus>
            <loadBalanceStrategy>DO_NOT_LOAD_BALANCE</loadBalanceStrategy>
            <name></name>
            <selectedRelationships>matched</selectedRelationships>
            <source>
                <groupId>318f3af6-162f-3813-0000-000000000000</groupId>
                <id>0693945b-ab7a-36e5-0000-000000000000</id>
                <type>PROCESSOR</type>
            </source>
            <zIndex>0</zIndex>
        </connections>
        <connections>
            <id>8e9f8dc0-a03c-3df5-0000-000000000000</id>
            <parentGroupId>318f3af6-162f-3813-0000-000000000000</parentGroupId>
            <backPressureDataSizeThreshold>1 GB</backPressureDataSizeThreshold>
            <backPressureObjectThreshold>10000</backPressureObjectThreshold>
            <bends>
                <x>2214.342529296875</x>
                <y>286.1420249938965</y>
            </bends>
            <bends>
                <x>2214.342529296875</x>
                <y>336.1420249938965</y>
            </bends>
            <destination>
                <groupId>318f3af6-162f-3813-0000-000000000000</groupId>
                <id>468434ca-b8a4-3056-0000-000000000000</id>
                <type>PROCESSOR</type>
            </destination>
            <flowFileExpiration>0 sec</flowFileExpiration>
            <labelIndex>1</labelIndex>
            <loadBalanceCompression>DO_NOT_COMPRESS</loadBalanceCompression>
            <loadBalancePartitionAttribute></loadBalancePartitionAttribute>
            <loadBalanceStatus>LOAD_BALANCE_NOT_CONFIGURED</loadBalanceStatus>
            <loadBalanceStrategy>DO_NOT_LOAD_BALANCE</loadBalanceStrategy>
            <name></name>
            <selectedRelationships>failure</selectedRelationships>
            <source>
                <groupId>318f3af6-162f-3813-0000-000000000000</groupId>
                <id>468434ca-b8a4-3056-0000-000000000000</id>
                <type>PROCESSOR</type>
            </source>
            <zIndex>0</zIndex>
        </connections>
        <connections>
            <id>90369ddb-204e-3230-0000-000000000000</id>
            <parentGroupId>318f3af6-162f-3813-0000-000000000000</parentGroupId>
            <backPressureDataSizeThreshold>1 GB</backPressureDataSizeThreshold>
            <backPressureObjectThreshold>10000</backPressureObjectThreshold>
            <destination>
                <groupId>318f3af6-162f-3813-0000-000000000000</groupId>
                <id>0693945b-ab7a-36e5-0000-000000000000</id>
                <type>PROCESSOR</type>
            </destination>
            <flowFileExpiration>0 sec</flowFileExpiration>
            <labelIndex>1</labelIndex>
            <loadBalanceCompression>DO_NOT_COMPRESS</loadBalanceCompression>
            <loadBalancePartitionAttribute></loadBalancePartitionAttribute>
            <loadBalanceStatus>LOAD_BALANCE_NOT_CONFIGURED</loadBalanceStatus>
            <loadBalanceStrategy>DO_NOT_LOAD_BALANCE</loadBalanceStrategy>
            <name></name>
            <selectedRelationships>success</selectedRelationships>
            <source>
                <groupId>318f3af6-162f-3813-0000-000000000000</groupId>
                <id>d06dde27-9bcd-3bde-0000-000000000000</id>
                <type>PROCESSOR</type>
            </source>
            <zIndex>0</zIndex>
        </connections>
        <connections>
            <id>b6943a8d-dfb7-340a-0000-000000000000</id>
            <parentGroupId>318f3af6-162f-3813-0000-000000000000</parentGroupId>
            <backPressureDataSizeThreshold>1 GB</backPressureDataSizeThreshold>
            <backPressureObjectThreshold>10000</backPressureObjectThreshold>
            <destination>
                <groupId>318f3af6-162f-3813-0000-000000000000</groupId>
                <id>7c331bf2-b7ee-3f9c-0000-000000000000</id>
                <type>PROCESSOR</type>
            </destination>
            <flowFileExpiration>0 sec</flowFileExpiration>
            <labelIndex>1</labelIndex>
            <loadBalanceCompression>DO_NOT_COMPRESS</loadBalanceCompression>
            <loadBalancePartitionAttribute></loadBalancePartitionAttribute>
            <loadBalanceStatus>LOAD_BALANCE_NOT_CONFIGURED</loadBalanceStatus>
            <loadBalanceStrategy>DO_NOT_LOAD_BALANCE</loadBalanceStrategy>
            <name></name>
            <selectedRelationships>success</selectedRelationships>
            <source>
                <groupId>318f3af6-162f-3813-0000-000000000000</groupId>
                <id>8ba51d01-5f30-3bc5-0000-000000000000</id>
                <type>PROCESSOR</type>
            </source>
            <zIndex>0</zIndex>
        </connections>
        <connections>
            <id>b72e7246-20af-309b-0000-000000000000</id>
            <parentGroupId>318f3af6-162f-3813-0000-000000000000</parentGroupId>
            <backPressureDataSizeThreshold>1 GB</backPressureDataSizeThreshold>
            <backPressureObjectThreshold>10000</backPressureObjectThreshold>
            <destination>
                <groupId>318f3af6-162f-3813-0000-000000000000</groupId>
                <id>8ba51d01-5f30-3bc5-0000-000000000000</id>
                <type>PROCESSOR</type>
            </destination>
            <flowFileExpiration>0 sec</flowFileExpiration>
            <labelIndex>1</labelIndex>
            <loadBalanceCompression>DO_NOT_COMPRESS</loadBalanceCompression>
            <loadBalancePartitionAttribute></loadBalancePartitionAttribute>
            <loadBalanceStatus>LOAD_BALANCE_NOT_CONFIGURED</loadBalanceStatus>
            <loadBalanceStrategy>DO_NOT_LOAD_BALANCE</loadBalanceStrategy>
            <name></name>
            <selectedRelationships>matched</selectedRelationships>
            <source>
                <groupId>318f3af6-162f-3813-0000-000000000000</groupId>
                <id>e0499510-f6c9-33bd-0000-000000000000</id>
                <type>PROCESSOR</type>
            </source>
            <zIndex>0</zIndex>
        </connections>
        <connections>
            <id>bd15077e-5cd8-37be-0000-000000000000</id>
            <parentGroupId>318f3af6-162f-3813-0000-000000000000</parentGroupId>
            <backPressureDataSizeThreshold>1 GB</backPressureDataSizeThreshold>
            <backPressureObjectThreshold>10000</backPressureObjectThreshold>
            <destination>
                <groupId>318f3af6-162f-3813-0000-000000000000</groupId>
                <id>e0499510-f6c9-33bd-0000-000000000000</id>
                <type>PROCESSOR</type>
            </destination>
            <flowFileExpiration>0 sec</flowFileExpiration>
            <labelIndex>1</labelIndex>
            <loadBalanceCompression>DO_NOT_COMPRESS</loadBalanceCompression>
            <loadBalancePartitionAttribute></loadBalancePartitionAttribute>
            <loadBalanceStatus>LOAD_BALANCE_NOT_CONFIGURED</loadBalanceStatus>
            <loadBalanceStrategy>DO_NOT_LOAD_BALANCE</loadBalanceStrategy>
            <name></name>
            <selectedRelationships>success</selectedRelationships>
            <source>
                <groupId>318f3af6-162f-3813-0000-000000000000</groupId>
                <id>3f1fc979-fb58-3119-0000-000000000000</id>
                <type>PROCESSOR</type>
            </source>
            <zIndex>0</zIndex>
        </connections>
        <connections>
            <id>fb21f0ac-a5b4-3169-0000-000000000000</id>
            <parentGroupId>318f3af6-162f-3813-0000-000000000000</parentGroupId>
            <backPressureDataSizeThreshold>1 GB</backPressureDataSizeThreshold>
            <backPressureObjectThreshold>10000</backPressureObjectThreshold>
            <destination>
                <groupId>318f3af6-162f-3813-0000-000000000000</groupId>
                <id>028b1655-7bb8-32dc-0000-000000000000</id>
                <type>PROCESSOR</type>
            </destination>
            <flowFileExpiration>0 sec</flowFileExpiration>
            <labelIndex>1</labelIndex>
            <loadBalanceCompression>DO_NOT_COMPRESS</loadBalanceCompression>
            <loadBalancePartitionAttribute></loadBalancePartitionAttribute>
            <loadBalanceStatus>LOAD_BALANCE_NOT_CONFIGURED</loadBalanceStatus>
            <loadBalanceStrategy>DO_NOT_LOAD_BALANCE</loadBalanceStrategy>
            <name></name>
            <selectedRelationships>success</selectedRelationships>
            <source>
                <groupId>318f3af6-162f-3813-0000-000000000000</groupId>
                <id>7c331bf2-b7ee-3f9c-0000-000000000000</id>
                <type>PROCESSOR</type>
            </source>
            <zIndex>0</zIndex>
        </connections>
        <processors>
            <id>028b1655-7bb8-32dc-0000-000000000000</id>
            <parentGroupId>318f3af6-162f-3813-0000-000000000000</parentGroupId>
            <position>
                <x>1376.0</x>
                <y>472.0</y>
            </position>
            <bundle>
                <artifact>nifi-standard-nar</artifact>
                <group>org.apache.nifi</group>
                <version>1.12.1</version>
            </bundle>
            <config>
                <bulletinLevel>WARN</bulletinLevel>
                <comments></comments>
                <concurrentlySchedulableTaskCount>1</concurrentlySchedulableTaskCount>
                <descriptors>
                    <entry>
                        <key>Attributes List</key>
                        <value>
                            <name>Attributes List</name>
                        </value>
                    </entry>
                    <entry>
                        <key>attributes-to-json-regex</key>
                        <value>
                            <name>attributes-to-json-regex</name>
                        </value>
                    </entry>
                    <entry>
                        <key>Destination</key>
                        <value>
                            <name>Destination</name>
                        </value>
                    </entry>
                    <entry>
                        <key>Include Core Attributes</key>
                        <value>
                            <name>Include Core Attributes</name>
                        </value>
                    </entry>
                    <entry>
                        <key>Null Value</key>
                        <value>
                            <name>Null Value</name>
                        </value>
                    </entry>
                </descriptors>
                <executionNode>ALL</executionNode>
                <lossTolerant>false</lossTolerant>
                <penaltyDuration>30 sec</penaltyDuration>
                <properties>
                    <entry>
                        <key>Attributes List</key>
                    </entry>
                    <entry>
                        <key>attributes-to-json-regex</key>
                    </entry>
                    <entry>
                        <key>Destination</key>
                        <value>flowfile-content</value>
                    </entry>
                    <entry>
                        <key>Include Core Attributes</key>
                        <value>true</value>
                    </entry>
                    <entry>
                        <key>Null Value</key>
                        <value>false</value>
                    </entry>
                </properties>
                <runDurationMillis>0</runDurationMillis>
                <schedulingPeriod>0 sec</schedulingPeriod>
                <schedulingStrategy>TIMER_DRIVEN</schedulingStrategy>
                <yieldDuration>1 sec</yieldDuration>
            </config>
            <executionNodeRestricted>false</executionNodeRestricted>
            <name>AttributesToJSON</name>
            <relationships>
                <autoTerminate>true</autoTerminate>
                <name>failure</name>
            </relationships>
            <relationships>
                <autoTerminate>false</autoTerminate>
                <name>success</name>
            </relationships>
            <state>RUNNING</state>
            <style/>
            <type>org.apache.nifi.processors.standard.AttributesToJSON</type>
        </processors>
        <processors>
            <id>0693945b-ab7a-36e5-0000-000000000000</id>
            <parentGroupId>318f3af6-162f-3813-0000-000000000000</parentGroupId>
            <position>
                <x>0.0</x>
                <y>224.0</y>
            </position>
            <bundle>
                <artifact>nifi-standard-nar</artifact>
                <group>org.apache.nifi</group>
                <version>1.12.1</version>
            </bundle>
            <config>
                <bulletinLevel>WARN</bulletinLevel>
                <comments></comments>
                <concurrentlySchedulableTaskCount>1</concurrentlySchedulableTaskCount>
                <descriptors>
                    <entry>
                        <key>Destination</key>
                        <value>
                            <name>Destination</name>
                        </value>
                    </entry>
                    <entry>
                        <key>Return Type</key>
                        <value>
                            <name>Return Type</name>
                        </value>
                    </entry>
                    <entry>
                        <key>Path Not Found Behavior</key>
                        <value>
                            <name>Path Not Found Behavior</name>
                        </value>
                    </entry>
                    <entry>
                        <key>Null Value Representation</key>
                        <value>
                            <name>Null Value Representation</name>
                        </value>
                    </entry>
                    <entry>
                        <key>syslog.facility</key>
                        <value>
                            <name>syslog.facility</name>
                        </value>
                    </entry>
                    <entry>
                        <key>syslog.from-host</key>
                        <value>
                            <name>syslog.from-host</name>
                        </value>
                    </entry>
                    <entry>
                        <key>syslog.message</key>
                        <value>
                            <name>syslog.message</name>
                        </value>
                    </entry>
                    <entry>
                        <key>syslog.priority</key>
                        <value>
                            <name>syslog.priority</name>
                        </value>
                    </entry>
                    <entry>
                        <key>syslog.timereported</key>
                        <value>
                            <name>syslog.timereported</name>
                        </value>
                    </entry>
                </descriptors>
                <executionNode>ALL</executionNode>
                <lossTolerant>false</lossTolerant>
                <penaltyDuration>30 sec</penaltyDuration>
                <properties>
                    <entry>
                        <key>Destination</key>
                        <value>flowfile-attribute</value>
                    </entry>
                    <entry>
                        <key>Return Type</key>
                        <value>auto-detect</value>
                    </entry>
                    <entry>
                        <key>Path Not Found Behavior</key>
                        <value>ignore</value>
                    </entry>
                    <entry>
                        <key>Null Value Representation</key>
                        <value>empty string</value>
                    </entry>
                    <entry>
                        <key>syslog.facility</key>
                        <value>$.facility</value>
                    </entry>
                    <entry>
                        <key>syslog.from-host</key>
                        <value>$.fromhost</value>
                    </entry>
                    <entry>
                        <key>syslog.message</key>
                        <value>$.message</value>
                    </entry>
                    <entry>
                        <key>syslog.priority</key>
                        <value>$.priority</value>
                    </entry>
                    <entry>
                        <key>syslog.timereported</key>
                        <value>$.timereported</value>
                    </entry>
                </properties>
                <runDurationMillis>0</runDurationMillis>
                <schedulingPeriod>0 sec</schedulingPeriod>
                <schedulingStrategy>TIMER_DRIVEN</schedulingStrategy>
                <yieldDuration>1 sec</yieldDuration>
            </config>
            <executionNodeRestricted>false</executionNodeRestricted>
            <name>EvaluateJsonPath</name>
            <relationships>
                <autoTerminate>true</autoTerminate>
                <name>failure</name>
            </relationships>
            <relationships>
                <autoTerminate>false</autoTerminate>
                <name>matched</name>
            </relationships>
            <relationships>
                <autoTerminate>true</autoTerminate>
                <name>unmatched</name>
            </relationships>
            <state>RUNNING</state>
            <style/>
            <type>org.apache.nifi.processors.standard.EvaluateJsonPath</type>
        </processors>
        <processors>
            <id>3f1fc979-fb58-3119-0000-000000000000</id>
            <parentGroupId>318f3af6-162f-3813-0000-000000000000</parentGroupId>
            <position>
                <x>584.0</x>
                <y>240.0</y>
            </position>
            <bundle>
                <artifact>nifi-standard-nar</artifact>
                <group>org.apache.nifi</group>
                <version>1.12.1</version>
            </bundle>
            <config>
                <bulletinLevel>WARN</bulletinLevel>
                <comments></comments>
                <concurrentlySchedulableTaskCount>1</concurrentlySchedulableTaskCount>
                <descriptors>
                    <entry>
                        <key>Regular Expression</key>
                        <value>
                            <name>Regular Expression</name>
                        </value>
                    </entry>
                    <entry>
                        <key>Replacement Value</key>
                        <value>
                            <name>Replacement Value</name>
                        </value>
                    </entry>
                    <entry>
                        <key>Character Set</key>
                        <value>
                            <name>Character Set</name>
                        </value>
                    </entry>
                    <entry>
                        <key>Maximum Buffer Size</key>
                        <value>
                            <name>Maximum Buffer Size</name>
                        </value>
                    </entry>
                    <entry>
                        <key>Replacement Strategy</key>
                        <value>
                            <name>Replacement Strategy</name>
                        </value>
                    </entry>
                    <entry>
                        <key>Evaluation Mode</key>
                        <value>
                            <name>Evaluation Mode</name>
                        </value>
                    </entry>
                    <entry>
                        <key>Line-by-Line Evaluation Mode</key>
                        <value>
                            <name>Line-by-Line Evaluation Mode</name>
                        </value>
                    </entry>
                </descriptors>
                <executionNode>ALL</executionNode>
                <lossTolerant>false</lossTolerant>
                <penaltyDuration>30 sec</penaltyDuration>
                <properties>
                    <entry>
                        <key>Regular Expression</key>
                        <value>^.*$</value>
                    </entry>
                    <entry>
                        <key>Replacement Value</key>
                        <value>${syslog.message}</value>
                    </entry>
                    <entry>
                        <key>Character Set</key>
                        <value>UTF-8</value>
                    </entry>
                    <entry>
                        <key>Maximum Buffer Size</key>
                        <value>1 MB</value>
                    </entry>
                    <entry>
                        <key>Replacement Strategy</key>
                        <value>Regex Replace</value>
                    </entry>
                    <entry>
                        <key>Evaluation Mode</key>
                        <value>Entire text</value>
                    </entry>
                    <entry>
                        <key>Line-by-Line Evaluation Mode</key>
                        <value>All</value>
                    </entry>
                </properties>
                <runDurationMillis>0</runDurationMillis>
                <schedulingPeriod>0 sec</schedulingPeriod>
                <schedulingStrategy>TIMER_DRIVEN</schedulingStrategy>
                <yieldDuration>1 sec</yieldDuration>
            </config>
            <executionNodeRestricted>false</executionNodeRestricted>
            <name>ReplaceText</name>
            <relationships>
                <autoTerminate>true</autoTerminate>
                <name>failure</name>
            </relationships>
            <relationships>
                <autoTerminate>false</autoTerminate>
                <name>success</name>
            </relationships>
            <state>RUNNING</state>
            <style/>
            <type>org.apache.nifi.processors.standard.ReplaceText</type>
        </processors>
        <processors>
            <id>468434ca-b8a4-3056-0000-000000000000</id>
            <parentGroupId>318f3af6-162f-3813-0000-000000000000</parentGroupId>
            <position>
                <x>1744.0</x>
                <y>248.0</y>
            </position>
            <bundle>
                <artifact>nifi-kafka-2-6-nar</artifact>
                <group>org.apache.nifi</group>
                <version>1.12.1</version>
            </bundle>
            <config>
                <bulletinLevel>WARN</bulletinLevel>
                <comments></comments>
                <concurrentlySchedulableTaskCount>1</concurrentlySchedulableTaskCount>
                <descriptors>
                    <entry>
                        <key>bootstrap.servers</key>
                        <value>
                            <name>bootstrap.servers</name>
                        </value>
                    </entry>
                    <entry>
                        <key>security.protocol</key>
                        <value>
                            <name>security.protocol</name>
                        </value>
                    </entry>
                    <entry>
                        <key>sasl.mechanism</key>
                        <value>
                            <name>sasl.mechanism</name>
                        </value>
                    </entry>
                    <entry>
                        <key>sasl.kerberos.service.name</key>
                        <value>
                            <name>sasl.kerberos.service.name</name>
                        </value>
                    </entry>
                    <entry>
                        <key>kerberos-credentials-service</key>
                        <value>
                            <identifiesControllerService>org.apache.nifi.kerberos.KerberosCredentialsService</identifiesControllerService>
                            <name>kerberos-credentials-service</name>
                        </value>
                    </entry>
                    <entry>
                        <key>sasl.kerberos.principal</key>
                        <value>
                            <name>sasl.kerberos.principal</name>
                        </value>
                    </entry>
                    <entry>
                        <key>sasl.kerberos.keytab</key>
                        <value>
                            <name>sasl.kerberos.keytab</name>
                        </value>
                    </entry>
                    <entry>
                        <key>sasl.username</key>
                        <value>
                            <name>sasl.username</name>
                        </value>
                    </entry>
                    <entry>
                        <key>sasl.password</key>
                        <value>
                            <name>sasl.password</name>
                        </value>
                    </entry>
                    <entry>
                        <key>sasl.token.auth</key>
                        <value>
                            <name>sasl.token.auth</name>
                        </value>
                    </entry>
                    <entry>
                        <key>ssl.context.service</key>
                        <value>
                            <identifiesControllerService>org.apache.nifi.ssl.SSLContextService</identifiesControllerService>
                            <name>ssl.context.service</name>
                        </value>
                    </entry>
                    <entry>
                        <key>topic</key>
                        <value>
                            <name>topic</name>
                        </value>
                    </entry>
                    <entry>
                        <key>acks</key>
                        <value>
                            <name>acks</name>
                        </value>
                    </entry>
                    <entry>
                        <key>use-transactions</key>
                        <value>
                            <name>use-transactions</name>
                        </value>
                    </entry>
                    <entry>
                        <key>transactional-id-prefix</key>
                        <value>
                            <name>transactional-id-prefix</name>
                        </value>
                    </entry>
                    <entry>
                        <key>attribute-name-regex</key>
                        <value>
                            <name>attribute-name-regex</name>
                        </value>
                    </entry>
                    <entry>
                        <key>message-header-encoding</key>
                        <value>
                            <name>message-header-encoding</name>
                        </value>
                    </entry>
                    <entry>
                        <key>kafka-key</key>
                        <value>
                            <name>kafka-key</name>
                        </value>
                    </entry>
                    <entry>
                        <key>key-attribute-encoding</key>
                        <value>
                            <name>key-attribute-encoding</name>
                        </value>
                    </entry>
                    <entry>
                        <key>message-demarcator</key>
                        <value>
                            <name>message-demarcator</name>
                        </value>
                    </entry>
                    <entry>
                        <key>max.request.size</key>
                        <value>
                            <name>max.request.size</name>
                        </value>
                    </entry>
                    <entry>
                        <key>ack.wait.time</key>
                        <value>
                            <name>ack.wait.time</name>
                        </value>
                    </entry>
                    <entry>
                        <key>max.block.ms</key>
                        <value>
                            <name>max.block.ms</name>
                        </value>
                    </entry>
                    <entry>
                        <key>partitioner.class</key>
                        <value>
                            <name>partitioner.class</name>
                        </value>
                    </entry>
                    <entry>
                        <key>partition</key>
                        <value>
                            <name>partition</name>
                        </value>
                    </entry>
                    <entry>
                        <key>compression.type</key>
                        <value>
                            <name>compression.type</name>
                        </value>
                    </entry>
                </descriptors>
                <executionNode>ALL</executionNode>
                <lossTolerant>false</lossTolerant>
                <penaltyDuration>30 sec</penaltyDuration>
                <properties>
                    <entry>
                        <key>bootstrap.servers</key>
                        <value>kafka-kafka-bootstrap:9092</value>
                    </entry>
                    <entry>
                        <key>security.protocol</key>
                        <value>PLAINTEXT</value>
                    </entry>
                    <entry>
                        <key>sasl.mechanism</key>
                        <value>GSSAPI</value>
                    </entry>
                    <entry>
                        <key>sasl.kerberos.service.name</key>
                    </entry>
                    <entry>
                        <key>kerberos-credentials-service</key>
                    </entry>
                    <entry>
                        <key>sasl.kerberos.principal</key>
                    </entry>
                    <entry>
                        <key>sasl.kerberos.keytab</key>
                    </entry>
                    <entry>
                        <key>sasl.username</key>
                    </entry>
                    <entry>
                        <key>sasl.password</key>
                    </entry>
                    <entry>
                        <key>sasl.token.auth</key>
                        <value>false</value>
                    </entry>
                    <entry>
                        <key>ssl.context.service</key>
                    </entry>
                    <entry>
                        <key>topic</key>
                        <value>{{ kafka_topic }}</value>
                    </entry>
                    <entry>
                        <key>acks</key>
                        <value>0</value>
                    </entry>
                    <entry>
                        <key>use-transactions</key>
                        <value>false</value>
                    </entry>
                    <entry>
                        <key>transactional-id-prefix</key>
                    </entry>
                    <entry>
                        <key>attribute-name-regex</key>
                    </entry>
                    <entry>
                        <key>message-header-encoding</key>
                        <value>UTF-8</value>
                    </entry>
                    <entry>
                        <key>kafka-key</key>
                        <value>test-key</value>
                    </entry>
                    <entry>
                        <key>key-attribute-encoding</key>
                        <value>utf-8</value>
                    </entry>
                    <entry>
                        <key>message-demarcator</key>
                    </entry>
                    <entry>
                        <key>max.request.size</key>
                        <value>1 MB</value>
                    </entry>
                    <entry>
                        <key>ack.wait.time</key>
                        <value>5 secs</value>
                    </entry>
                    <entry>
                        <key>max.block.ms</key>
                        <value>5 sec</value>
                    </entry>
                    <entry>
                        <key>partitioner.class</key>
                        <value>org.apache.kafka.clients.producer.internals.DefaultPartitioner</value>
                    </entry>
                    <entry>
                        <key>partition</key>
                    </entry>
                    <entry>
                        <key>compression.type</key>
                        <value>none</value>
                    </entry>
                </properties>
                <runDurationMillis>0</runDurationMillis>
                <schedulingPeriod>0 sec</schedulingPeriod>
                <schedulingStrategy>TIMER_DRIVEN</schedulingStrategy>
                <yieldDuration>1 sec</yieldDuration>
            </config>
            <executionNodeRestricted>false</executionNodeRestricted>
            <name>PublishKafka_2_6</name>
            <relationships>
                <autoTerminate>false</autoTerminate>
                <name>failure</name>
            </relationships>
            <relationships>
                <autoTerminate>true</autoTerminate>
                <name>success</name>
            </relationships>
            <state>RUNNING</state>
            <style/>
            <type>org.apache.nifi.processors.kafka.pubsub.PublishKafka_2_6</type>
        </processors>
        <processors>
            <id>7c331bf2-b7ee-3f9c-0000-000000000000</id>
            <parentGroupId>318f3af6-162f-3813-0000-000000000000</parentGroupId>
            <position>
                <x>704.0</x>
                <y>472.0</y>
            </position>
            <bundle>
                <artifact>nifi-update-attribute-nar</artifact>
                <group>org.apache.nifi</group>
                <version>1.12.1</version>
            </bundle>
            <config>
                <bulletinLevel>WARN</bulletinLevel>
                <comments></comments>
                <concurrentlySchedulableTaskCount>1</concurrentlySchedulableTaskCount>
                <descriptors>
                    <entry>
                        <key>Delete Attributes Expression</key>
                        <value>
                            <name>Delete Attributes Expression</name>
                        </value>
                    </entry>
                    <entry>
                        <key>Store State</key>
                        <value>
                            <name>Store State</name>
                        </value>
                    </entry>
                    <entry>
                        <key>Stateful Variables Initial Value</key>
                        <value>
                            <name>Stateful Variables Initial Value</name>
                        </value>
                    </entry>
                    <entry>
                        <key>canonical-value-lookup-cache-size</key>
                        <value>
                            <name>canonical-value-lookup-cache-size</name>
                        </value>
                    </entry>
                </descriptors>
                <executionNode>ALL</executionNode>
                <lossTolerant>false</lossTolerant>
                <penaltyDuration>30 sec</penaltyDuration>
                <properties>
                    <entry>
                        <key>Delete Attributes Expression</key>
                        <value>^(?!httpd|syslog).+</value>
                    </entry>
                    <entry>
                        <key>Store State</key>
                        <value>Do not store state</value>
                    </entry>
                    <entry>
                        <key>Stateful Variables Initial Value</key>
                    </entry>
                    <entry>
                        <key>canonical-value-lookup-cache-size</key>
                        <value>100</value>
                    </entry>
                </properties>
                <runDurationMillis>0</runDurationMillis>
                <schedulingPeriod>0 sec</schedulingPeriod>
                <schedulingStrategy>TIMER_DRIVEN</schedulingStrategy>
                <yieldDuration>1 sec</yieldDuration>
            </config>
            <executionNodeRestricted>false</executionNodeRestricted>
            <name>UpdateAttribute</name>
            <relationships>
                <autoTerminate>false</autoTerminate>
                <name>success</name>
            </relationships>
            <state>RUNNING</state>
            <style/>
            <type>org.apache.nifi.processors.attributes.UpdateAttribute</type>
        </processors>
        <processors>
            <id>8ba51d01-5f30-3bc5-0000-000000000000</id>
            <parentGroupId>318f3af6-162f-3813-0000-000000000000</parentGroupId>
            <position>
                <x>8.0</x>
                <y>440.0</y>
            </position>
            <bundle>
                <artifact>nifi-scripting-nar</artifact>
                <group>org.apache.nifi</group>
                <version>1.12.1</version>
            </bundle>
            <config>
                <bulletinLevel>WARN</bulletinLevel>
                <comments></comments>
                <concurrentlySchedulableTaskCount>1</concurrentlySchedulableTaskCount>
                <descriptors>
                    <entry>
                        <key>Script Engine</key>
                        <value>
                            <name>Script Engine</name>
                        </value>
                    </entry>
                    <entry>
                        <key>Script File</key>
                        <value>
                            <name>Script File</name>
                        </value>
                    </entry>
                    <entry>
                        <key>Script Body</key>
                        <value>
                            <name>Script Body</name>
                        </value>
                    </entry>
                    <entry>
                        <key>Module Directory</key>
                        <value>
                            <name>Module Directory</name>
                        </value>
                    </entry>
                </descriptors>
                <executionNode>ALL</executionNode>
                <lossTolerant>false</lossTolerant>
                <penaltyDuration>30 sec</penaltyDuration>
                <properties>
                    <entry>
                        <key>Script Engine</key>
                        <value>ruby</value>
                    </entry>
                    <entry>
                        <key>Script File</key>
                    </entry>
                    <entry>
                        <key>Script Body</key>
                        <value>if (flowfile = session.get)
  flowfile.getAttributes.each do |k, v|
    if k =~ /^grok\.(.+)/
      flowfile = session.removeAttribute(flowfile, k)
      attr = $1
      # don't keep any uppercase attrs, as these are the
      # grok params.
      if attr =~ /[a-z]+/
        flowfile = session.putAttribute(flowfile, "httpd." + attr, v)
      end
    end
  end
  session.transfer(flowfile, REL_SUCCESS)
end</value>
                    </entry>
                    <entry>
                        <key>Module Directory</key>
                    </entry>
                </properties>
                <runDurationMillis>0</runDurationMillis>
                <schedulingPeriod>0 sec</schedulingPeriod>
                <schedulingStrategy>TIMER_DRIVEN</schedulingStrategy>
                <yieldDuration>1 sec</yieldDuration>
            </config>
            <executionNodeRestricted>false</executionNodeRestricted>
            <name>ExecuteScript</name>
            <relationships>
                <autoTerminate>true</autoTerminate>
                <name>failure</name>
            </relationships>
            <relationships>
                <autoTerminate>false</autoTerminate>
                <name>success</name>
            </relationships>
            <state>RUNNING</state>
            <style/>
            <type>org.apache.nifi.processors.script.ExecuteScript</type>
        </processors>
        <processors>
            <id>d06dde27-9bcd-3bde-0000-000000000000</id>
            <parentGroupId>318f3af6-162f-3813-0000-000000000000</parentGroupId>
            <position>
                <x>8.0</x>
                <y>0.0</y>
            </position>
            <bundle>
                <artifact>nifi-standard-nar</artifact>
                <group>org.apache.nifi</group>
                <version>1.12.1</version>
            </bundle>
            <config>
                <bulletinLevel>WARN</bulletinLevel>
                <comments></comments>
                <concurrentlySchedulableTaskCount>1</concurrentlySchedulableTaskCount>
                <descriptors>
                    <entry>
                        <key>Base Path</key>
                        <value>
                            <name>Base Path</name>
                        </value>
                    </entry>
                    <entry>
                        <key>Listening Port</key>
                        <value>
                            <name>Listening Port</name>
                        </value>
                    </entry>
                    <entry>
                        <key>Max Data to Receive per Second</key>
                        <value>
                            <name>Max Data to Receive per Second</name>
                        </value>
                    </entry>
                    <entry>
                        <key>SSL Context Service</key>
                        <value>
                            <identifiesControllerService>org.apache.nifi.ssl.RestrictedSSLContextService</identifiesControllerService>
                            <name>SSL Context Service</name>
                        </value>
                    </entry>
                    <entry>
                        <key>Authorized DN Pattern</key>
                        <value>
                            <name>Authorized DN Pattern</name>
                        </value>
                    </entry>
                    <entry>
                        <key>Max Unconfirmed Flowfile Time</key>
                        <value>
                            <name>Max Unconfirmed Flowfile Time</name>
                        </value>
                    </entry>
                    <entry>
                        <key>HTTP Headers to receive as Attributes (Regex)</key>
                        <value>
                            <name>HTTP Headers to receive as Attributes (Regex)</name>
                        </value>
                    </entry>
                    <entry>
                        <key>Return Code</key>
                        <value>
                            <name>Return Code</name>
                        </value>
                    </entry>
                    <entry>
                        <key>multipart-request-max-size</key>
                        <value>
                            <name>multipart-request-max-size</name>
                        </value>
                    </entry>
                    <entry>
                        <key>multipart-read-buffer-size</key>
                        <value>
                            <name>multipart-read-buffer-size</name>
                        </value>
                    </entry>
                </descriptors>
                <executionNode>ALL</executionNode>
                <lossTolerant>false</lossTolerant>
                <penaltyDuration>30 sec</penaltyDuration>
                <properties>
                    <entry>
                        <key>Base Path</key>
                        <value>contentListener</value>
                    </entry>
                    <entry>
                        <key>Listening Port</key>
                        <value>2055</value>
                    </entry>
                    <entry>
                        <key>Max Data to Receive per Second</key>
                    </entry>
                    <entry>
                        <key>SSL Context Service</key>
                    </entry>
                    <entry>
                        <key>Authorized DN Pattern</key>
                        <value>.*</value>
                    </entry>
                    <entry>
                        <key>Max Unconfirmed Flowfile Time</key>
                        <value>60 secs</value>
                    </entry>
                    <entry>
                        <key>HTTP Headers to receive as Attributes (Regex)</key>
                    </entry>
                    <entry>
                        <key>Return Code</key>
                        <value>200</value>
                    </entry>
                    <entry>
                        <key>multipart-request-max-size</key>
                        <value>1 MB</value>
                    </entry>
                    <entry>
                        <key>multipart-read-buffer-size</key>
                        <value>512 KB</value>
                    </entry>
                </properties>
                <runDurationMillis>0</runDurationMillis>
                <schedulingPeriod>0 sec</schedulingPeriod>
                <schedulingStrategy>TIMER_DRIVEN</schedulingStrategy>
                <yieldDuration>1 sec</yieldDuration>
            </config>
            <executionNodeRestricted>false</executionNodeRestricted>
            <name>ListenHTTP</name>
            <relationships>
                <autoTerminate>false</autoTerminate>
                <name>success</name>
            </relationships>
            <state>RUNNING</state>
            <style/>
            <type>org.apache.nifi.processors.standard.ListenHTTP</type>
        </processors>
        <processors>
            <id>e0499510-f6c9-33bd-0000-000000000000</id>
            <parentGroupId>318f3af6-162f-3813-0000-000000000000</parentGroupId>
            <position>
                <x>1200.0</x>
                <y>240.0</y>
            </position>
            <bundle>
                <artifact>nifi-standard-nar</artifact>
                <group>org.apache.nifi</group>
                <version>1.12.1</version>
            </bundle>
            <config>
                <bulletinLevel>WARN</bulletinLevel>
                <comments></comments>
                <concurrentlySchedulableTaskCount>1</concurrentlySchedulableTaskCount>
                <descriptors>
                    <entry>
                        <key>Grok Expression</key>
                        <value>
                            <name>Grok Expression</name>
                        </value>
                    </entry>
                    <entry>
                        <key>Grok Pattern file</key>
                        <value>
                            <name>Grok Pattern file</name>
                        </value>
                    </entry>
                    <entry>
                        <key>Destination</key>
                        <value>
                            <name>Destination</name>
                        </value>
                    </entry>
                    <entry>
                        <key>Character Set</key>
                        <value>
                            <name>Character Set</name>
                        </value>
                    </entry>
                    <entry>
                        <key>Maximum Buffer Size</key>
                        <value>
                            <name>Maximum Buffer Size</name>
                        </value>
                    </entry>
                    <entry>
                        <key>Named captures only</key>
                        <value>
                            <name>Named captures only</name>
                        </value>
                    </entry>
                    <entry>
                        <key>Keep Empty Captures</key>
                        <value>
                            <name>Keep Empty Captures</name>
                        </value>
                    </entry>
                </descriptors>
                <executionNode>ALL</executionNode>
                <lossTolerant>false</lossTolerant>
                <penaltyDuration>30 sec</penaltyDuration>
                <properties>
                    <entry>
                        <key>Grok Expression</key>
                        <value>%{IPORHOST:clientip} %{USER:ident} %{USER:auth} \[%{HTTPDATE:timestamp}\] "(?:%{WORD:verb} %{NOTSPACE:request}(?: HTTP/%{NUMBER:httpversion})?|%{DATA:rawrequest})" %{NUMBER:response} (?:%{NUMBER:bytes}|-) %{QS:referrer} %{QS:agent}</value>
                    </entry>
                    <entry>
                        <key>Grok Pattern file</key>
                    </entry>
                    <entry>
                        <key>Destination</key>
                        <value>flowfile-attribute</value>
                    </entry>
                    <entry>
                        <key>Character Set</key>
                        <value>UTF-8</value>
                    </entry>
                    <entry>
                        <key>Maximum Buffer Size</key>
                        <value>1 MB</value>
                    </entry>
                    <entry>
                        <key>Named captures only</key>
                        <value>false</value>
                    </entry>
                    <entry>
                        <key>Keep Empty Captures</key>
                        <value>true</value>
                    </entry>
                </properties>
                <runDurationMillis>0</runDurationMillis>
                <schedulingPeriod>0 sec</schedulingPeriod>
                <schedulingStrategy>TIMER_DRIVEN</schedulingStrategy>
                <yieldDuration>1 sec</yieldDuration>
            </config>
            <executionNodeRestricted>false</executionNodeRestricted>
            <name>ExtractGrok</name>
            <relationships>
                <autoTerminate>false</autoTerminate>
                <name>matched</name>
            </relationships>
            <relationships>
                <autoTerminate>true</autoTerminate>
                <name>unmatched</name>
            </relationships>
            <state>RUNNING</state>
            <style/>
            <type>org.apache.nifi.processors.standard.ExtractGrok</type>
        </processors>
    </snippet>
    <timestamp>04/11/2021 08:00:56 UTC</timestamp>
</template>
